rewrite/__init__.py
rewrite/execution.py
rewrite/markers.py
rewrite/parser.py
rewrite/result.py
rewrite/style.py
rewrite/test.py
rewrite/tree.py
rewrite/utils.py
rewrite/visitor.py
rewrite/java/__init__.py
rewrite/java/extensions.py
rewrite/java/markers.py
rewrite/java/support_types.py
rewrite/java/tree.py
rewrite/java/visitor.py
rewrite/java/remote/__init__.py
rewrite/java/remote/extensions.py
rewrite/java/remote/receiver.py
rewrite/java/remote/register.py
rewrite/java/remote/sender.py
rewrite/python/__init__.py
rewrite/python/_parser_visitor.py
rewrite/python/extensions.py
rewrite/python/markers.py
rewrite/python/parser.py
rewrite/python/printer.py
rewrite/python/style.py
rewrite/python/support_types.py
rewrite/python/templating.py
rewrite/python/tree.py
rewrite/python/type_mapping.py
rewrite/python/visitor.py
rewrite/python/format/__init__.py
rewrite/python/format/auto_format.py
rewrite/python/format/blank_lines.py
rewrite/python/format/minimum_viable_spacing.py
rewrite/python/format/normalize_format.py
rewrite/python/format/normalize_line_breaks_visitor.py
rewrite/python/format/normalize_tabs_or_spaces.py
rewrite/python/format/remove_trailing_whitespace_visitor.py
rewrite/python/format/spaces_visitor.py
rewrite/python/format/tabs_and_indents_visitor.py
rewrite/python/remote/__init__.py
rewrite/python/remote/extensions.py
rewrite/python/remote/receiver.py
rewrite/python/remote/sender.py
rewrite/python/utils/__init__.py
rewrite/python/utils/tree_visiting_printer.py
openrewrite-1.44.3.dist-info/METADATA
openrewrite-1.44.3.dist-info/WHEEL
openrewrite-1.44.3.dist-info/top_level.txt
openrewrite-1.44.3.dist-info/RECORD
