Metadata-Version: 2.4
Name: openrewrite
Version: 1.44.3
Summary: OpenRewrite is a mass automated refactoring engine.
Author-email: "Moderne Inc." <support@moderne.io>
License: Moderne, Inc. Commercial License
Project-URL: Homepage, https://github.com/openrewrite/rewrite-python/rewrite
Project-URL: Repository, https://github.com/openrewrite/rewrite-python.git
Project-URL: Issues, https://github.com/openrewrite/rewrite-python/issues
Classifier: Development Status :: 4 - Beta
Classifier: Intended Audience :: Developers
Classifier: Programming Language :: Python :: 3.12
Requires-Python: <4,>=3.9
Requires-Dist: pytest>=8.3.4
Requires-Dist: more-itertools>=10.4.0
Requires-Dist: openrewrite-remote
Requires-Dist: cbor2>=5.6.5
Requires-Dist: pytype>=2024.9.13
